{
  "kind": "collectionType",
  "collectionName": "places",
  "info": {
    "singularName": "place",
    "pluralName": "places",
    "displayName": "Place",
    "description": ""
  },
  "options": {
    "draftAndPublish": false
  },
  "pluginOptions": {},
  "attributes": {
    "location": {
      "type": "json",
      "pluginOptions": {
        "map-field": {
          "enabled": true
        }
      },
      "required": false
    },
    "title": {
      "type": "string",
      "required": true,
      "unique": true
    },
    "description": {
      "type": "text"
    },
    "media": {
      "type": "media",
      "multiple": true,
      "required": false,
      "allowedTypes": [
        "images",
        "files",
        "videos",
        "audios"
      ]
    },
    "cover": {
      "type": "media",
      "multiple": false,
      "required": false,
      "allowedTypes": [
        "images",
        "files",
        "videos",
        "audios"
      ]
    },
    "slug": {
      "type": "uid",
      "targetField": "title"
    },
    "blog_posts": {
      "type": "relation",
      "relation": "manyToMany",
      "target": "api::blog-post.blog-post",
      "mappedBy": "places"
    }
  }
}
